{"scrutin": {"@xmlns": "http://schemas.assemblee-nationale.fr/referentiel", "@xmlns:xsi": "http://www.w3.org/2001/XMLSchema-instance", "uid": "VTANR5L15V980", "numero": "980", "organeRef": "PO717460", "legislature": "15", "sessionRef": "SCR5A2018O1", "seanceRef": "RUANR5L15S2018IDS21121", "dateScrutin": "2018-06-20", "quantiemeJourSeance": "1", "typeVote": {"codeTypeVote": "SPO", "libelleTypeVote": "scrutin public ordinaire", "typeMajorite": "majorit\u00e9 absolue des suffrages exprim\u00e9s"}, "sort": {"code": "adopt\u00e9", "libelle": "l'Assembl\u00e9e nationale a adopt\u00e9"}, "titre": "la proposition de r\u00e9solution pour une r\u00e9vision g\u00e9n\u00e9rale des taxes \u00e0 faibles rendement (art. 34-1 de la Constitution).", "demandeur": {"texte": "Pr\u00e9sident du groupe \"La R\u00e9publique en Marche\"", "referenceLegislative": null}, "objet": {"libelle": "la proposition de r\u00e9solution pour une r\u00e9vision g\u00e9n\u00e9rale des taxes \u00e0 faibles rendement (art. 34-1 de la Constitution).", "referenceLegislative": null}, "modePublicationDesVotes": "DecompteNominatif", "syntheseVote": {"nombreVotants": "57", "suffragesExprimes": "52", "nbrSuffragesRequis": "27", "annonce": "l'Assembl\u00e9e nationale a adopt\u00e9", "decompte": {"nonVotants": "2", "pour": "49", "contre": "3", "abstentions": "5", "nonVotantsVolontaires": "0"}}, "ventilationVotes": {"organe": {"organeRef": "PO717460", "groupes": {"groupe": [{"organeRef": "PO730964", "nombreMembresGroupe": "312", "vote": {"positionMajoritaire": "pour", "decompteVoix": {"nonVotants": "2", "pour": "35", "contre": "0", "abstentions": "0", "nonVotantsVolontaires": "0"}, "decompteNominatif": {"nonVotants": {"votant": [{"acteurRef": "PA332747", "mandatRef": "PM722798", "causePositionVote": "PAN"}, {"acteurRef": "PA721824", "mandatRef": "PM723394", "causePositionVote": "PSE"}]}, "pours": {"votant": [{"acteurRef": "PA267336", "mandatRef": "PM722434", "parDelegation": "false"}, {"acteurRef": "PA722190", "mandatRef": "PM723498", "parDelegation": "false"}, {"acteurRef": "PA720492", "mandatRef": "PM722980", "parDelegation": "false"}, {"acteurRef": "PA718794", "mandatRef": "PM722460", "parDelegation": "false"}, {"acteurRef": "PA719024", "mandatRef": "PM722536", "parDelegation": "false"}, {"acteurRef": "PA719186", "mandatRef": "PM722588", "parDelegation": "false"}, {"acteurRef": "PA719440", "mandatRef": "PM722664", "parDelegation": "false"}, {"acteurRef": "PA719472", "mandatRef": "PM722672", "parDelegation": "false"}, {"acteurRef": "PA719512", "mandatRef": "PM722682", "parDelegation": "false"}, {"acteurRef": "PA719710", "mandatRef": "PM722738", "parDelegation": "false"}, {"acteurRef": "PA719740", "mandatRef": "PM722748", "parDelegation": "false"}, {"acteurRef": "PA719798", "mandatRef": "PM722766", "parDelegation": "false"}, {"acteurRef": "PA719850", "mandatRef": "PM722780", "parDelegation": "false"}, {"acteurRef": "PA719922", "mandatRef": "PM722802", "parDelegation": "false"}, {"acteurRef": "PA720022", "mandatRef": "PM722836", "parDelegation": "false"}, {"acteurRef": "PA720030", "mandatRef": "PM722838", "parDelegation": "false"}, {"acteurRef": "PA720108", "mandatRef": "PM722862", "parDelegation": "false"}, {"acteurRef": "PA643175", "mandatRef": "PM722868", "parDelegation": "false"}, {"acteurRef": "PA720222", "mandatRef": "PM722896", "parDelegation": "false"}, {"acteurRef": "PA720268", "mandatRef": "PM722912", "parDelegation": "false"}, {"acteurRef": "PA720318", "mandatRef": "PM722928", "parDelegation": "false"}, {"acteurRef": "PA720520", "mandatRef": "PM722988", "parDelegation": "false"}, {"acteurRef": "PA720560", "mandatRef": "PM723000", "parDelegation": "false"}, {"acteurRef": "PA720878", "mandatRef": "PM723102", "parDelegation": "false"}, {"acteurRef": "PA721150", "mandatRef": "PM723188", "parDelegation": "false"}, {"acteurRef": "PA721158", "mandatRef": "PM723190", "parDelegation": "false"}, {"acteurRef": "PA721450", "mandatRef": "PM723278", "parDelegation": "false"}, {"acteurRef": "PA721466", "mandatRef": "PM723284", "parDelegation": "false"}, {"acteurRef": "PA721498", "mandatRef": "PM723294", "parDelegation": "false"}, {"acteurRef": "PA721584", "mandatRef": "PM723324", "parDelegation": "false"}, {"acteurRef": "PA721670", "mandatRef": "PM723350", "parDelegation": "false"}, {"acteurRef": "PA721764", "mandatRef": "PM723376", "parDelegation": "false"}, {"acteurRef": "PA721860", "mandatRef": "PM723404", "parDelegation": "false"}, {"acteurRef": "PA722244", "mandatRef": "PM723516", "parDelegation": "false"}, {"acteurRef": "PA722366", "mandatRef": "PM723554", "parDelegation": "false"}]}, "contres": null, "abstentions": null}}}, {"organeRef": "PO730934", "nombreMembresGroupe": "102", "vote": {"positionMajoritaire": "pour", "decompteVoix": {"nonVotants": "0", "pour": "6", "contre": "0", "abstentions": "2", "nonVotantsVolontaires": "2"}, "decompteNominatif": {"nonVotants": null, "pours": {"votant": [{"acteurRef": "PA2960", "mandatRef": "PM723006", "parDelegation": "false"}, {"acteurRef": "PA332523", "mandatRef": "PM722792", "parDelegation": "false"}, {"acteurRef": "PA719272", "mandatRef": "PM722612", "parDelegation": "false"}, {"acteurRef": "PA642847", "mandatRef": "PM722954", "parDelegation": "false"}, {"acteurRef": "PA721474", "mandatRef": "PM723286", "parDelegation": "false"}, {"acteurRef": "PA266793", "mandatRef": "PM722550", "parDelegation": "false"}]}, "contres": null, "abstentions": {"votant": [{"acteurRef": "PA609726", "mandatRef": "PM723426", "parDelegation": "false"}, {"acteurRef": "PA721314", "mandatRef": "PM723236", "parDelegation": "false"}]}}}}, {"organeRef": "PO730970", "nombreMembresGroupe": "47", "vote": {"positionMajoritaire": "pour", "decompteVoix": {"nonVotants": "0", "pour": "1", "contre": "0", "abstentions": "0", "nonVotantsVolontaires": "0"}, "decompteNominatif": {"nonVotants": null, "pours": {"votant": {"acteurRef": "PA720002", "mandatRef": "PM722830", "parDelegation": "false"}}, "contres": null, "abstentions": null}}}, {"organeRef": "PO744425", "nombreMembresGroupe": "32", "vote": {"positionMajoritaire": "pour", "decompteVoix": {"nonVotants": "0", "pour": "4", "contre": "0", "abstentions": "0", "nonVotantsVolontaires": "0"}, "decompteNominatif": {"nonVotants": null, "pours": {"votant": [{"acteurRef": "PA942", "mandatRef": "PM722900", "parDelegation": "false"}, {"acteurRef": "PA332228", "mandatRef": "PM722754", "parDelegation": "false"}, {"acteurRef": "PA720230", "mandatRef": "PM722898", "parDelegation": "false"}, {"acteurRef": "PA267766", "mandatRef": "PM722970", "parDelegation": "false"}]}, "contres": null, "abstentions": null}}}, {"organeRef": "PO730946", "nombreMembresGroupe": "30", "vote": {"positionMajoritaire": "pour", "decompteVoix": {"nonVotants": "0", "pour": "3", "contre": "0", "abstentions": "0", "nonVotantsVolontaires": "0"}, "decompteNominatif": {"nonVotants": null, "pours": {"votant": [{"acteurRef": "PA342415", "mandatRef": "PM722826", "parDelegation": "false"}, {"acteurRef": "PA608172", "mandatRef": "PM723048", "parDelegation": "false"}, {"acteurRef": "PA608695", "mandatRef": "PM723564", "parDelegation": "false"}]}, "contres": null, "abstentions": null}}}, {"organeRef": "PO723569", "nombreMembresGroupe": "21", "vote": {"positionMajoritaire": "abstention", "decompteVoix": {"nonVotants": "0", "pour": "0", "contre": "0", "abstentions": "3", "nonVotantsVolontaires": "3"}, "decompteNominatif": {"nonVotants": null, "pours": null, "contres": null, "abstentions": {"votant": [{"acteurRef": "PA720468", "mandatRef": "PM722972", "parDelegation": "false"}, {"acteurRef": "PA720606", "mandatRef": "PM723014", "parDelegation": "false"}, {"acteurRef": "PA720822", "mandatRef": "PM723086", "parDelegation": "false"}]}}}}, {"organeRef": "PO730958", "nombreMembresGroupe": "17", "vote": {"positionMajoritaire": "contre", "decompteVoix": {"nonVotants": "0", "pour": "0", "contre": "1", "abstentions": "0", "nonVotantsVolontaires": "0"}, "decompteNominatif": {"nonVotants": null, "pours": null, "contres": {"votant": {"acteurRef": "PA721202", "mandatRef": "PM723202", "parDelegation": "false"}}, "abstentions": null}}}, {"organeRef": "PO730940", "nombreMembresGroupe": "16", "vote": {"positionMajoritaire": "contre", "decompteVoix": {"nonVotants": "0", "pour": "0", "contre": "2", "abstentions": "0", "nonVotantsVolontaires": "0"}, "decompteNominatif": {"nonVotants": null, "pours": null, "contres": {"votant": [{"acteurRef": "PA718720", "mandatRef": "PM722436", "parDelegation": "false"}, {"acteurRef": "PA722110", "mandatRef": "PM723474", "parDelegation": "false"}]}, "abstentions": null}}}]}}}, "miseAuPoint": null}}