{"scrutin": {"@xmlns": "http://schemas.assemblee-nationale.fr/referentiel", "@xmlns:xsi": "http://www.w3.org/2001/XMLSchema-instance", "uid": "VTANR5L15V1392", "numero": "1392", "organeRef": "PO717460", "legislature": "15", "sessionRef": "SCR5A2019O1", "seanceRef": "RUANR5L15S2019IDS21337", "dateScrutin": "2018-11-13", "quantiemeJourSeance": "1", "typeVote": {"codeTypeVote": "SPO", "libelleTypeVote": "scrutin public ordinaire", "typeMajorite": "majorit\u00e9 absolue des suffrages exprim\u00e9s"}, "sort": {"code": "rejet\u00e9", "libelle": "L'Assembl\u00e9e nationale n'a pas adopt\u00e9"}, "titre": "l'amendement n\u00b0 1798 de M. Pradi\u00e9 \u00e0 l'article 39 et \u00e9tat B de la seconde partie du projet de loi de finances pour 2019 - Mission Enseignement scolaire (premi\u00e8re lecture).", "demandeur": {"texte": "Pr\u00e9sident du groupe \"Les R\u00e9publicains\"", "referenceLegislative": null}, "objet": {"libelle": "l'amendement n\u00b0 1798 de M. Pradi\u00e9 \u00e0 l'article 39 et \u00e9tat B de la seconde partie du projet de loi de finances pour 2019 - Mission Enseignement scolaire (premi\u00e8re lecture).", "referenceLegislative": null}, "modePublicationDesVotes": "DecompteNominatif", "syntheseVote": {"nombreVotants": "91", "suffragesExprimes": "90", "nbrSuffragesRequis": "46", "annonce": "L'Assembl\u00e9e nationale n'a pas adopt\u00e9", "decompte": {"nonVotants": "2", "pour": "34", "contre": "56", "abstentions": "1", "nonVotantsVolontaires": "0"}}, "ventilationVotes": {"organe": {"organeRef": "PO717460", "groupes": {"groupe": [{"organeRef": "PO730964", "nombreMembresGroupe": "308", "vote": {"positionMajoritaire": "contre", "decompteVoix": {"nonVotants": "1", "pour": "0", "contre": "51", "abstentions": "1", "nonVotantsVolontaires": "1"}, "decompteNominatif": {"nonVotants": {"votant": {"acteurRef": "PA606171", "mandatRef": "PM722632", "causePositionVote": "PAN"}}, "pours": null, "contres": {"votant": [{"acteurRef": "PA719668", "mandatRef": "PM722726", "parDelegation": "false"}, {"acteurRef": "PA722252", "mandatRef": "PM723518", "parDelegation": "false"}, {"acteurRef": "PA605963", "mandatRef": "PM722584", "parDelegation": "false"}, {"acteurRef": "PA720492", "mandatRef": "PM722980", "parDelegation": "false"}, {"acteurRef": "PA718682", "mandatRef": "PM722422", "parDelegation": "false"}, {"acteurRef": "PA718736", "mandatRef": "PM722440", "parDelegation": "false"}, {"acteurRef": "PA718794", "mandatRef": "PM722460", "parDelegation": "false"}, {"acteurRef": "PA718902", "mandatRef": "PM722496", "parDelegation": "false"}, {"acteurRef": "PA718944", "mandatRef": "PM722508", "parDelegation": "false"}, {"acteurRef": "PA719024", "mandatRef": "PM722536", "parDelegation": "false"}, {"acteurRef": "PA719032", "mandatRef": "PM722538", "parDelegation": "false"}, {"acteurRef": "PA719108", "mandatRef": "PM722564", "parDelegation": "false"}, {"acteurRef": "PA719170", "mandatRef": "PM722582", "parDelegation": "false"}, {"acteurRef": "PA719186", "mandatRef": "PM722588", "parDelegation": "false"}, {"acteurRef": "PA719230", "mandatRef": "PM722600", "parDelegation": "false"}, {"acteurRef": "PA719456", "mandatRef": "PM722668", "parDelegation": "false"}, {"acteurRef": "PA719472", "mandatRef": "PM722672", "parDelegation": "false"}, {"acteurRef": "PA719512", "mandatRef": "PM722682", "parDelegation": "false"}, {"acteurRef": "PA719728", "mandatRef": "PM722744", "parDelegation": "false"}, {"acteurRef": "PA719798", "mandatRef": "PM722766", "parDelegation": "false"}, {"acteurRef": "PA719830", "mandatRef": "PM722774", "parDelegation": "false"}, {"acteurRef": "PA719890", "mandatRef": "PM722790", "parDelegation": "false"}, {"acteurRef": "PA719980", "mandatRef": "PM722822", "parDelegation": "false"}, {"acteurRef": "PA720022", "mandatRef": "PM722836", "parDelegation": "false"}, {"acteurRef": "PA720030", "mandatRef": "PM722838", "parDelegation": "false"}, {"acteurRef": "PA643175", "mandatRef": "PM722868", "parDelegation": "false"}, {"acteurRef": "PA720138", "mandatRef": "PM722872", "parDelegation": "false"}, {"acteurRef": "PA720268", "mandatRef": "PM722912", "parDelegation": "false"}, {"acteurRef": "PA720310", "mandatRef": "PM722926", "parDelegation": "false"}, {"acteurRef": "PA720318", "mandatRef": "PM722928", "parDelegation": "false"}, {"acteurRef": "PA720362", "mandatRef": "PM722942", "parDelegation": "false"}, {"acteurRef": "PA720446", "mandatRef": "PM722966", "parDelegation": "false"}, {"acteurRef": "PA720520", "mandatRef": "PM722988", "parDelegation": "false"}, {"acteurRef": "PA720560", "mandatRef": "PM723000", "parDelegation": "false"}, {"acteurRef": "PA720568", "mandatRef": "PM723002", "parDelegation": "false"}, {"acteurRef": "PA720754", "mandatRef": "PM723066", "parDelegation": "false"}, {"acteurRef": "PA720814", "mandatRef": "PM723084", "parDelegation": "false"}, {"acteurRef": "PA720854", "mandatRef": "PM723096", "parDelegation": "false"}, {"acteurRef": "PA721218", "mandatRef": "PM723206", "parDelegation": "false"}, {"acteurRef": "PA721328", "mandatRef": "PM723240", "parDelegation": "false"}, {"acteurRef": "PA721336", "mandatRef": "PM723242", "parDelegation": "false"}, {"acteurRef": "PA721450", "mandatRef": "PM723278", "parDelegation": "false"}, {"acteurRef": "PA721584", "mandatRef": "PM723324", "parDelegation": "false"}, {"acteurRef": "PA721750", "mandatRef": "PM723372", "parDelegation": "false"}, {"acteurRef": "PA721946", "mandatRef": "PM723430", "parDelegation": "false"}, {"acteurRef": "PA722054", "mandatRef": "PM723460", "parDelegation": "false"}, {"acteurRef": "PA722086", "mandatRef": "PM723468", "parDelegation": "false"}, {"acteurRef": "PA722382", "mandatRef": "PM723558", "parDelegation": "false"}, {"acteurRef": "PA643205", "mandatRef": "PM723358", "parDelegation": "false"}, {"acteurRef": "PA718706", "mandatRef": "PM733715", "parDelegation": "false"}, {"acteurRef": "PA721956", "mandatRef": "PM733717", "parDelegation": "false"}]}, "abstentions": {"votant": {"acteurRef": "PA720074", "mandatRef": "PM722850", "parDelegation": "false"}}}}}, {"organeRef": "PO730934", "nombreMembresGroupe": "104", "vote": {"positionMajoritaire": "pour", "decompteVoix": {"nonVotants": "1", "pour": "22", "contre": "0", "abstentions": "0", "nonVotantsVolontaires": "0"}, "decompteNominatif": {"nonVotants": {"votant": {"acteurRef": "PA1874", "mandatRef": "PM722598", "causePositionVote": "PSE"}}, "pours": {"votant": [{"acteurRef": "PA345722", "mandatRef": "PM723428", "parDelegation": "false"}, {"acteurRef": "PA606712", "mandatRef": "PM722756", "parDelegation": "false"}, {"acteurRef": "PA2155", "mandatRef": "PM722490", "parDelegation": "false"}, {"acteurRef": "PA334843", "mandatRef": "PM723534", "parDelegation": "false"}, {"acteurRef": "PA267324", "mandatRef": "PM723292", "parDelegation": "false"}, {"acteurRef": "PA718850", "mandatRef": "PM722478", "parDelegation": "false"}, {"acteurRef": "PA266776", "mandatRef": "PM723542", "parDelegation": "false"}, {"acteurRef": "PA718838", "mandatRef": "PM722474", "parDelegation": "false"}, {"acteurRef": "PA1012", "mandatRef": "PM722418", "parDelegation": "false"}, {"acteurRef": "PA267450", "mandatRef": "PM722586", "parDelegation": "false"}, {"acteurRef": "PA720684", "mandatRef": "PM723040", "parDelegation": "false"}, {"acteurRef": "PA718780", "mandatRef": "PM722454", "parDelegation": "false"}, {"acteurRef": "PA643103", "mandatRef": "PM722614", "parDelegation": "false"}, {"acteurRef": "PA719318", "mandatRef": "PM722624", "parDelegation": "false"}, {"acteurRef": "PA643134", "mandatRef": "PM722824", "parDelegation": "false"}, {"acteurRef": "PA720100", "mandatRef": "PM722860", "parDelegation": "false"}, {"acteurRef": "PA720386", "mandatRef": "PM722948", "parDelegation": "false"}, {"acteurRef": "PA720630", "mandatRef": "PM723020", "parDelegation": "false"}, {"acteurRef": "PA266793", "mandatRef": "PM722550", "parDelegation": "false"}, {"acteurRef": "PA709315", "mandatRef": "PM722526", "parDelegation": "false"}, {"acteurRef": "PA712015", "mandatRef": "PM722448", "parDelegation": "false"}, {"acteurRef": "PA643089", "mandatRef": "PM758076", "parDelegation": "false"}]}, "contres": null, "abstentions": null}}}, {"organeRef": "PO730970", "nombreMembresGroupe": "46", "vote": {"positionMajoritaire": "contre", "decompteVoix": {"nonVotants": "0", "pour": "0", "contre": "4", "abstentions": "0", "nonVotantsVolontaires": "0"}, "decompteNominatif": {"nonVotants": null, "pours": null, "contres": {"votant": [{"acteurRef": "PA719044", "mandatRef": "PM722542", "parDelegation": "false"}, {"acteurRef": "PA719488", "mandatRef": "PM722676", "parDelegation": "false"}, {"acteurRef": "PA719640", "mandatRef": "PM722718", "parDelegation": "false"}, {"acteurRef": "PA720256", "mandatRef": "PM722908", "parDelegation": "false"}]}, "abstentions": null}}}, {"organeRef": "PO758835", "nombreMembresGroupe": "29", "vote": {"positionMajoritaire": "pour", "decompteVoix": {"nonVotants": "0", "pour": "6", "contre": "0", "abstentions": "0", "nonVotantsVolontaires": "0"}, "decompteNominatif": {"nonVotants": null, "pours": {"votant": [{"acteurRef": "PA605069", "mandatRef": "PM722424", "parDelegation": "false"}, {"acteurRef": "PA332614", "mandatRef": "PM722812", "parDelegation": "false"}, {"acteurRef": "PA342415", "mandatRef": "PM722826", "parDelegation": "false"}, {"acteurRef": "PA720988", "mandatRef": "PM723132", "parDelegation": "false"}, {"acteurRef": "PA608741", "mandatRef": "PM757984", "parDelegation": "false"}, {"acteurRef": "PA340357", "mandatRef": "PM747435", "parDelegation": "false"}]}, "contres": null, "abstentions": null}}}, {"organeRef": "PO744425", "nombreMembresGroupe": "28", "vote": {"positionMajoritaire": "contre", "decompteVoix": {"nonVotants": "0", "pour": "0", "contre": "1", "abstentions": "0", "nonVotantsVolontaires": "0"}, "decompteNominatif": {"nonVotants": null, "pours": null, "contres": {"votant": {"acteurRef": "PA720696", "mandatRef": "PM723044", "parDelegation": "false"}}, "abstentions": null}}}, {"organeRef": "PO730958", "nombreMembresGroupe": "17", "vote": {"positionMajoritaire": "pour", "decompteVoix": {"nonVotants": "0", "pour": "0", "contre": "0", "abstentions": "0", "nonVotantsVolontaires": "0"}, "decompteNominatif": {"nonVotants": null, "pours": null, "contres": null, "abstentions": null}}}, {"organeRef": "PO730940", "nombreMembresGroupe": "16", "vote": {"positionMajoritaire": "pour", "decompteVoix": {"nonVotants": "0", "pour": "3", "contre": "0", "abstentions": "0", "nonVotantsVolontaires": "0"}, "decompteNominatif": {"nonVotants": null, "pours": {"votant": [{"acteurRef": "PA689", "mandatRef": "PM723090", "parDelegation": "false"}, {"acteurRef": "PA722202", "mandatRef": "PM723502", "parDelegation": "false"}, {"acteurRef": "PA721896", "mandatRef": "PM723414", "parDelegation": "false"}]}, "contres": null, "abstentions": null}}}, {"organeRef": "PO759900", "nombreMembresGroupe": "16", "vote": {"positionMajoritaire": "pour", "decompteVoix": {"nonVotants": "0", "pour": "0", "contre": "0", "abstentions": "0", "nonVotantsVolontaires": "0"}, "decompteNominatif": {"nonVotants": null, "pours": null, "contres": null, "abstentions": null}}}, {"organeRef": "PO723569", "nombreMembresGroupe": "12", "vote": {"positionMajoritaire": "pour", "decompteVoix": {"nonVotants": "0", "pour": "3", "contre": "0", "abstentions": "0", "nonVotantsVolontaires": "0"}, "decompteNominatif": {"nonVotants": null, "pours": {"votant": [{"acteurRef": "PA719608", "mandatRef": "PM722710", "parDelegation": "false"}, {"acteurRef": "PA720798", "mandatRef": "PM723080", "parDelegation": "false"}, {"acteurRef": "PA721932", "mandatRef": "PM734586", "parDelegation": "false"}]}, "contres": null, "abstentions": null}}}]}}}, "miseAuPoint": null}}