{"acteur": {"@xmlns": "http://schemas.assemblee-nationale.fr/referentiel", "uid": {"@xmlns:xsi": "http://www.w3.org/2001/XMLSchema-instance", "@xsi:type": "IdActeur_type", "#text": "PA267200"}, "etatCivil": {"ident": {"civ": "M.", "prenom": "S\u00e9bastien", "nom": "Huyghe", "alpha": "Huyghe", "trigramme": "SHY"}, "infoNaissance": {"dateNais": "1969-10-25", "villeNais": "B\u00e9thune", "depNais": "Pas-de-Calais", "paysNais": "France"}, "dateDeces": {"@xmlns:xsi": "http://www.w3.org/2001/XMLSchema-instance", "@xsi:nil": "true"}}, "profession": {"libelleCourant": "Notaire", "socProcINSEE": {"catSocPro": "Professions lib\u00e9rales et assimil\u00e9s", "famSocPro": "Cadres et professions intellectuelles sup\u00e9rieures"}}, "uri_hatvp": "https://www.hatvp.fr/pages_nominatives/huyghe-sebastien", "adresses": {"adresse": [{"@xmlns:xsi": "http://www.w3.org/2001/XMLSchema-instance", "@xsi:type": "AdressePostale_Type", "uid": "AD13648", "type": "2", "typeLibelle": "Adresse publi\u00e9e de circonscription", "poids": "22", "adresseDeRattachement": null, "intitule": null, "numeroRue": "234", "nomRue": "Rue du G\u00e9n\u00e9ral de Gaulle,", "complementAdresse": "BP 10099", "codePostal": "59635", "ville": "Wattignies Cedex"}, {"@xmlns:xsi": "http://www.w3.org/2001/XMLSchema-instance", "@xsi:type": "AdresseTelephonique_Type", "uid": "AD13650", "type": "11", "typeLibelle": "T\u00e9l\u00e9phone", "poids": "22", "adresseDeRattachement": "AD13648", "valElec": "03 20 60 26 26"}, {"@xmlns:xsi": "http://www.w3.org/2001/XMLSchema-instance", "@xsi:type": "AdressePostale_Type", "uid": "AD386858", "type": "0", "typeLibelle": "Adresse officielle", "poids": "1", "adresseDeRattachement": null, "intitule": "Assembl\u00e9e nationale,", "numeroRue": "126", "nomRue": "Rue de l'Universit\u00e9,", "complementAdresse": null, "codePostal": "75355", "ville": "Paris 07 SP"}, {"@xmlns:xsi": "http://www.w3.org/2001/XMLSchema-instance", "@xsi:type": "AdresseMail_Type", "uid": "AD391992", "type": "15", "typeLibelle": "M\u00e8l", "poids": null, "adresseDeRattachement": null, "valElec": "sebastien.huyghe@assemblee-nationale.fr"}, {"@xmlns:xsi": "http://www.w3.org/2001/XMLSchema-instance", "@xsi:type": "AdresseSiteWeb_Type", "uid": "AD726090", "type": "25", "typeLibelle": "Facebook", "poids": null, "adresseDeRattachement": null, "valElec": "shuyghe.depute"}, {"@xmlns:xsi": "http://www.w3.org/2001/XMLSchema-instance", "@xsi:type": "AdresseSiteWeb_Type", "uid": "AD726422", "type": "24", "typeLibelle": "Twitter", "poids": null, "adresseDeRattachement": null, "valElec": "@SebastienHuyghe"}]}, "mandats": {"mandat": [{"@xmlns:xsi": "http://www.w3.org/2001/XMLSchema-instance", "@xsi:type": "MandatAvecSuppleant_Type", "uid": "PM756337", "acteurRef": "PA267200", "legislature": "15", "typeOrgane": "OFFPAR", "dateDebut": "2018-05-24", "datePublication": "2018-05-24", "dateFin": null, "preseance": "24", "nominPrincipale": "1", "infosQualite": {"codeQualite": "Membre", "libQualite": "Membre", "libQualiteSex": "Membre"}, "organes": {"organeRef": "PO756284"}, "suppleants": null}, {"@xmlns:xsi": "http://www.w3.org/2001/XMLSchema-instance", "@xsi:type": "MandatSimple_Type", "uid": "PM745683", "acteurRef": "PA267200", "legislature": null, "typeOrgane": "PARPOL", "dateDebut": "2017-12-01", "datePublication": null, "dateFin": null, "preseance": "5", "nominPrincipale": "1", "infosQualite": {"codeQualite": "Membre", "libQualite": "Membre", "libQualiteSex": "Membre"}, "organes": {"organeRef": "PO710396"}}, {"@xmlns:xsi": "http://www.w3.org/2001/XMLSchema-instance", "@xsi:type": "MandatSimple_Type", "uid": "PM738920", "acteurRef": "PA267200", "legislature": "15", "typeOrgane": "GEVI", "dateDebut": "2017-10-10", "datePublication": null, "dateFin": null, "preseance": "20", "nominPrincipale": "1", "infosQualite": {"codeQualite": "Membre", "libQualite": "Membre", "libQualiteSex": "Membre"}, "organes": {"organeRef": "PO733217"}}, {"@xmlns:xsi": "http://www.w3.org/2001/XMLSchema-instance", "@xsi:type": "MandatMission_Type", "uid": "PM750177", "acteurRef": "PA267200", "legislature": "15", "typeOrgane": "MISINFO", "dateDebut": "2018-02-14", "datePublication": null, "dateFin": null, "preseance": "10", "nominPrincipale": "1", "infosQualite": {"codeQualite": "Membre", "libQualite": "Membre", "libQualiteSex": "Membre"}, "organes": {"organeRef": "PO750141"}, "libelle": null, "missionSuivanteRef": null, "missionPrecedenteRef": null}, {"@xmlns:xsi": "http://www.w3.org/2001/XMLSchema-instance", "@xsi:type": "MandatSimple_Type", "uid": "PM743049", "acteurRef": "PA267200", "legislature": "15", "typeOrgane": "ORGEXTPARL", "dateDebut": "2017-11-10", "datePublication": "2017-11-11", "dateFin": null, "preseance": "20", "nominPrincipale": "1", "infosQualite": {"codeQualite": "Titulaire", "libQualite": "Membre titulaire", "libQualiteSex": "Membre titulaire"}, "organes": {"organeRef": "PO430925"}}, {"@xmlns:xsi": "http://www.w3.org/2001/XMLSchema-instance", "@xsi:type": "MandatSimple_Type", "uid": "PM731354", "acteurRef": "PA267200", "legislature": "15", "typeOrgane": "GP", "dateDebut": "2017-06-27", "datePublication": "2017-06-28", "dateFin": null, "preseance": "20", "nominPrincipale": "1", "infosQualite": {"codeQualite": "Membre", "libQualite": "Membre du", "libQualiteSex": "Membre du"}, "organes": {"organeRef": "PO730934"}}, {"@xmlns:xsi": "http://www.w3.org/2001/XMLSchema-instance", "@xsi:type": "MandatSimple_Type", "uid": "PM731867", "acteurRef": "PA267200", "legislature": "15", "typeOrgane": "COMPER", "dateDebut": "2017-06-29", "datePublication": "2017-06-29", "dateFin": null, "preseance": "32", "nominPrincipale": "1", "infosQualite": {"codeQualite": "Membre", "libQualite": "Membre", "libQualiteSex": "Membre"}, "organes": {"organeRef": "PO59051"}}, {"@xmlns:xsi": "http://www.w3.org/2001/XMLSchema-instance", "@xsi:type": "MandatSimple_Type", "uid": "PM754523", "acteurRef": "PA267200", "legislature": "15", "typeOrgane": "GE", "dateDebut": "2018-03-29", "datePublication": null, "dateFin": null, "preseance": "20", "nominPrincipale": "1", "infosQualite": {"codeQualite": "Membre", "libQualite": "Membre", "libQualiteSex": "Membre"}, "organes": {"organeRef": "PO746957"}}, {"@xmlns:xsi": "http://www.w3.org/2001/XMLSchema-instance", "@xsi:type": "MandatSimple_Type", "uid": "PM749448", "acteurRef": "PA267200", "legislature": "15", "typeOrgane": "GE", "dateDebut": "2018-02-12", "datePublication": null, "dateFin": null, "preseance": "20", "nominPrincipale": "1", "infosQualite": {"codeQualite": "Membre", "libQualite": "Membre", "libQualiteSex": "Membre"}, "organes": {"organeRef": "PO746894"}}, {"@xmlns:xsi": "http://www.w3.org/2001/XMLSchema-instance", "@xsi:type": "MandatSimple_Type", "uid": "PM752650", "acteurRef": "PA267200", "legislature": "15", "typeOrgane": "GE", "dateDebut": "2018-03-06", "datePublication": null, "dateFin": null, "preseance": "20", "nominPrincipale": "1", "infosQualite": {"codeQualite": "Membre", "libQualite": "Membre", "libQualiteSex": "Membre"}, "organes": {"organeRef": "PO747220"}}, {"@xmlns:xsi": "http://www.w3.org/2001/XMLSchema-instance", "@xsi:type": "MandatSimple_Type", "uid": "PM752259", "acteurRef": "PA267200", "legislature": "15", "typeOrgane": "GE", "dateDebut": "2018-03-05", "datePublication": null, "dateFin": null, "preseance": "20", "nominPrincipale": "1", "infosQualite": {"codeQualite": "Membre", "libQualite": "Membre", "libQualiteSex": "Membre"}, "organes": {"organeRef": "PO746679"}}, {"@xmlns:xsi": "http://www.w3.org/2001/XMLSchema-instance", "@xsi:type": "MandatSimple_Type", "uid": "PM752442", "acteurRef": "PA267200", "legislature": "15", "typeOrgane": "GE", "dateDebut": "2018-03-06", "datePublication": null, "dateFin": null, "preseance": "20", "nominPrincipale": "1", "infosQualite": {"codeQualite": "Membre", "libQualite": "Membre", "libQualiteSex": "Membre"}, "organes": {"organeRef": "PO746920"}}, {"@xmlns:xsi": "http://www.w3.org/2001/XMLSchema-instance", "@xsi:type": "MandatSimple_Type", "uid": "PM753459", "acteurRef": "PA267200", "legislature": "15", "typeOrgane": "GE", "dateDebut": "2018-03-14", "datePublication": null, "dateFin": null, "preseance": "20", "nominPrincipale": "1", "infosQualite": {"codeQualite": "Membre", "libQualite": "Membre", "libQualiteSex": "Membre"}, "organes": {"organeRef": "PO746987"}}, {"@xmlns:xsi": "http://www.w3.org/2001/XMLSchema-instance", "@xsi:type": "MandatSimple_Type", "uid": "PM755830", "acteurRef": "PA267200", "legislature": "15", "typeOrgane": "GE", "dateDebut": "2018-04-23", "datePublication": null, "dateFin": null, "preseance": "20", "nominPrincipale": "0", "infosQualite": {"codeQualite": "Membre", "libQualite": "Membre", "libQualiteSex": "Membre"}, "organes": {"organeRef": "PO746684"}}, {"@xmlns:xsi": "http://www.w3.org/2001/XMLSchema-instance", "@xsi:type": "MandatSimple_Type", "uid": "PM755832", "acteurRef": "PA267200", "legislature": "15", "typeOrgane": "GE", "dateDebut": "2018-04-23", "datePublication": null, "dateFin": null, "preseance": "12", "nominPrincipale": "1", "infosQualite": {"codeQualite": "Secr\u00e9taire", "libQualite": "Secr\u00e9taire", "libQualiteSex": "Secr\u00e9taire"}, "organes": {"organeRef": "PO746684"}}, {"@xmlns:xsi": "http://www.w3.org/2001/XMLSchema-instance", "@xsi:type": "MandatSimple_Type", "uid": "PM752275", "acteurRef": "PA267200", "legislature": "15", "typeOrgane": "GE", "dateDebut": "2018-03-05", "datePublication": null, "dateFin": null, "preseance": "20", "nominPrincipale": "0", "infosQualite": {"codeQualite": "Membre", "libQualite": "Membre", "libQualiteSex": "Membre"}, "organes": {"organeRef": "PO746837"}}, {"@xmlns:xsi": "http://www.w3.org/2001/XMLSchema-instance", "@xsi:type": "MandatSimple_Type", "uid": "PM755524", "acteurRef": "PA267200", "legislature": "15", "typeOrgane": "GE", "dateDebut": "2018-04-11", "datePublication": null, "dateFin": null, "preseance": "12", "nominPrincipale": "1", "infosQualite": {"codeQualite": "Secr\u00e9taire", "libQualite": "Secr\u00e9taire", "libQualiteSex": "Secr\u00e9taire"}, "organes": {"organeRef": "PO746837"}}, {"@xmlns:xsi": "http://www.w3.org/2001/XMLSchema-instance", "@xsi:type": "MandatSimple_Type", "uid": "PM753309", "acteurRef": "PA267200", "legislature": "15", "typeOrgane": "GE", "dateDebut": "2018-03-13", "datePublication": null, "dateFin": null, "preseance": "20", "nominPrincipale": "1", "infosQualite": {"codeQualite": "Membre", "libQualite": "Membre", "libQualiteSex": "Membre"}, "organes": {"organeRef": "PO747047"}}, {"@xmlns:xsi": "http://www.w3.org/2001/XMLSchema-instance", "@xsi:type": "MandatSimple_Type", "uid": "PM758799", "acteurRef": "PA267200", "legislature": "15", "typeOrgane": "GE", "dateDebut": "2018-09-06", "datePublication": null, "dateFin": null, "preseance": "20", "nominPrincipale": "1", "infosQualite": {"codeQualite": "Membre", "libQualite": "Membre", "libQualiteSex": "Membre"}, "organes": {"organeRef": "PO747281"}}, {"@xmlns:xsi": "http://www.w3.org/2001/XMLSchema-instance", "@xsi:type": "MandatSimple_Type", "uid": "PM751430", "acteurRef": "PA267200", "legislature": "15", "typeOrgane": "GE", "dateDebut": "2018-02-21", "datePublication": null, "dateFin": null, "preseance": "20", "nominPrincipale": "0", "infosQualite": {"codeQualite": "Membre", "libQualite": "Membre", "libQualiteSex": "Membre"}, "organes": {"organeRef": "PO746644"}}, {"@xmlns:xsi": "http://www.w3.org/2001/XMLSchema-instance", "@xsi:type": "MandatSimple_Type", "uid": "PM738922", "acteurRef": "PA267200", "legislature": "15", "typeOrgane": "GA", "dateDebut": "2017-10-10", "datePublication": null, "dateFin": null, "preseance": "20", "nominPrincipale": "1", "infosQualite": {"codeQualite": "Membre", "libQualite": "Membre", "libQualiteSex": "Membre"}, "organes": {"organeRef": "PO733072"}}, {"@xmlns:xsi": "http://www.w3.org/2001/XMLSchema-instance", "@xsi:type": "MandatSimple_Type", "uid": "PM738924", "acteurRef": "PA267200", "legislature": "15", "typeOrgane": "GA", "dateDebut": "2017-10-10", "datePublication": null, "dateFin": null, "preseance": "20", "nominPrincipale": "1", "infosQualite": {"codeQualite": "Membre", "libQualite": "Membre", "libQualiteSex": "Membre"}, "organes": {"organeRef": "PO733307"}}, {"@xmlns:xsi": "http://www.w3.org/2001/XMLSchema-instance", "@xsi:type": "MandatSimple_Type", "uid": "PM738926", "acteurRef": "PA267200", "legislature": "15", "typeOrgane": "GA", "dateDebut": "2017-10-10", "datePublication": null, "dateFin": null, "preseance": "20", "nominPrincipale": "1", "infosQualite": {"codeQualite": "Membre", "libQualite": "Membre", "libQualiteSex": "Membre"}, "organes": {"organeRef": "PO733342"}}, {"@xmlns:xsi": "http://www.w3.org/2001/XMLSchema-instance", "@xsi:type": "MandatSimple_Type", "uid": "PM738930", "acteurRef": "PA267200", "legislature": "15", "typeOrgane": "GA", "dateDebut": "2017-10-10", "datePublication": null, "dateFin": null, "preseance": "20", "nominPrincipale": "1", "infosQualite": {"codeQualite": "Membre", "libQualite": "Membre", "libQualiteSex": "Membre"}, "organes": {"organeRef": "PO733412"}}, {"@xmlns:xsi": "http://www.w3.org/2001/XMLSchema-instance", "@xsi:type": "MandatSimple_Type", "uid": "PM738928", "acteurRef": "PA267200", "legislature": "15", "typeOrgane": "GA", "dateDebut": "2017-10-10", "datePublication": null, "dateFin": null, "preseance": "20", "nominPrincipale": "1", "infosQualite": {"codeQualite": "Membre", "libQualite": "Membre", "libQualiteSex": "Membre"}, "organes": {"organeRef": "PO733372"}}, {"@xmlns:xsi": "http://www.w3.org/2001/XMLSchema-instance", "@xsi:type": "MandatSimple_Type", "uid": "PM738932", "acteurRef": "PA267200", "legislature": "15", "typeOrgane": "GA", "dateDebut": "2017-10-10", "datePublication": null, "dateFin": null, "preseance": "20", "nominPrincipale": "1", "infosQualite": {"codeQualite": "Membre", "libQualite": "Membre", "libQualiteSex": "Membre"}, "organes": {"organeRef": "PO733567"}}, {"@xmlns:xsi": "http://www.w3.org/2001/XMLSchema-instance", "@xsi:type": "MandatSimple_Type", "uid": "PM738934", "acteurRef": "PA267200", "legislature": "15", "typeOrgane": "GA", "dateDebut": "2017-10-10", "datePublication": null, "dateFin": null, "preseance": "20", "nominPrincipale": "1", "infosQualite": {"codeQualite": "Membre", "libQualite": "Membre", "libQualiteSex": "Membre"}, "organes": {"organeRef": "PO733577"}}, {"@xmlns:xsi": "http://www.w3.org/2001/XMLSchema-instance", "@xsi:type": "MandatSimple_Type", "uid": "PM738936", "acteurRef": "PA267200", "legislature": "15", "typeOrgane": "GA", "dateDebut": "2017-10-10", "datePublication": null, "dateFin": null, "preseance": "20", "nominPrincipale": "1", "infosQualite": {"codeQualite": "Membre", "libQualite": "Membre", "libQualiteSex": "Membre"}, "organes": {"organeRef": "PO733617"}}, {"@xmlns:xsi": "http://www.w3.org/2001/XMLSchema-instance", "@xsi:type": "MandatSimple_Type", "uid": "PM738938", "acteurRef": "PA267200", "legislature": "15", "typeOrgane": "GA", "dateDebut": "2017-10-10", "datePublication": null, "dateFin": null, "preseance": "20", "nominPrincipale": "1", "infosQualite": {"codeQualite": "Membre", "libQualite": "Membre", "libQualiteSex": "Membre"}, "organes": {"organeRef": "PO733637"}}, {"@xmlns:xsi": "http://www.w3.org/2001/XMLSchema-instance", "@xsi:type": "MandatSimple_Type", "uid": "PM738921", "acteurRef": "PA267200", "legislature": "15", "typeOrgane": "GA", "dateDebut": "2017-10-10", "datePublication": null, "dateFin": null, "preseance": "20", "nominPrincipale": "1", "infosQualite": {"codeQualite": "Membre", "libQualite": "Membre", "libQualiteSex": "Membre"}, "organes": {"organeRef": "PO733057"}}, {"@xmlns:xsi": "http://www.w3.org/2001/XMLSchema-instance", "@xsi:type": "MandatSimple_Type", "uid": "PM738923", "acteurRef": "PA267200", "legislature": "15", "typeOrgane": "GA", "dateDebut": "2017-10-10", "datePublication": null, "dateFin": null, "preseance": "20", "nominPrincipale": "1", "infosQualite": {"codeQualite": "Membre", "libQualite": "Membre", "libQualiteSex": "Membre"}, "organes": {"organeRef": "PO733117"}}, {"@xmlns:xsi": "http://www.w3.org/2001/XMLSchema-instance", "@xsi:type": "MandatSimple_Type", "uid": "PM738925", "acteurRef": "PA267200", "legislature": "15", "typeOrgane": "GA", "dateDebut": "2017-10-10", "datePublication": null, "dateFin": null, "preseance": "20", "nominPrincipale": "1", "infosQualite": {"codeQualite": "Membre", "libQualite": "Membre", "libQualiteSex": "Membre"}, "organes": {"organeRef": "PO733322"}}, {"@xmlns:xsi": "http://www.w3.org/2001/XMLSchema-instance", "@xsi:type": "MandatSimple_Type", "uid": "PM738927", "acteurRef": "PA267200", "legislature": "15", "typeOrgane": "GA", "dateDebut": "2017-10-10", "datePublication": null, "dateFin": null, "preseance": "20", "nominPrincipale": "1", "infosQualite": {"codeQualite": "Membre", "libQualite": "Membre", "libQualiteSex": "Membre"}, "organes": {"organeRef": "PO733357"}}, {"@xmlns:xsi": "http://www.w3.org/2001/XMLSchema-instance", "@xsi:type": "MandatSimple_Type", "uid": "PM738931", "acteurRef": "PA267200", "legislature": "15", "typeOrgane": "GA", "dateDebut": "2017-10-10", "datePublication": null, "dateFin": null, "preseance": "20", "nominPrincipale": "1", "infosQualite": {"codeQualite": "Membre", "libQualite": "Membre", "libQualiteSex": "Membre"}, "organes": {"organeRef": "PO733437"}}, {"@xmlns:xsi": "http://www.w3.org/2001/XMLSchema-instance", "@xsi:type": "MandatSimple_Type", "uid": "PM738929", "acteurRef": "PA267200", "legislature": "15", "typeOrgane": "GA", "dateDebut": "2017-10-10", "datePublication": null, "dateFin": null, "preseance": "20", "nominPrincipale": "1", "infosQualite": {"codeQualite": "Membre", "libQualite": "Membre", "libQualiteSex": "Membre"}, "organes": {"organeRef": "PO733397"}}, {"@xmlns:xsi": "http://www.w3.org/2001/XMLSchema-instance", "@xsi:type": "MandatSimple_Type", "uid": "PM738933", "acteurRef": "PA267200", "legislature": "15", "typeOrgane": "GA", "dateDebut": "2017-10-10", "datePublication": null, "dateFin": null, "preseance": "20", "nominPrincipale": "1", "infosQualite": {"codeQualite": "Membre", "libQualite": "Membre", "libQualiteSex": "Membre"}, "organes": {"organeRef": "PO733572"}}, {"@xmlns:xsi": "http://www.w3.org/2001/XMLSchema-instance", "@xsi:type": "MandatSimple_Type", "uid": "PM738935", "acteurRef": "PA267200", "legislature": "15", "typeOrgane": "GA", "dateDebut": "2017-10-10", "datePublication": null, "dateFin": null, "preseance": "20", "nominPrincipale": "1", "infosQualite": {"codeQualite": "Membre", "libQualite": "Membre", "libQualiteSex": "Membre"}, "organes": {"organeRef": "PO733607"}}, {"@xmlns:xsi": "http://www.w3.org/2001/XMLSchema-instance", "@xsi:type": "MandatSimple_Type", "uid": "PM738937", "acteurRef": "PA267200", "legislature": "15", "typeOrgane": "GA", "dateDebut": "2017-10-10", "datePublication": null, "dateFin": null, "preseance": "20", "nominPrincipale": "1", "infosQualite": {"codeQualite": "Membre", "libQualite": "Membre", "libQualiteSex": "Membre"}, "organes": {"organeRef": "PO733632"}}, {"@xmlns:xsi": "http://www.w3.org/2001/XMLSchema-instance", "@xsi:type": "MandatSimple_Type", "uid": "PM753340", "acteurRef": "PA267200", "legislature": "15", "typeOrgane": "GE", "dateDebut": "2018-03-06", "datePublication": null, "dateFin": null, "preseance": "8", "nominPrincipale": "1", "infosQualite": {"codeQualite": "Vice-Pr\u00e9sident", "libQualite": "Vice-Pr\u00e9sident", "libQualiteSex": "Vice-Pr\u00e9sident"}, "organes": {"organeRef": "PO746644"}}, {"@xmlns:xsi": "http://www.w3.org/2001/XMLSchema-instance", "@xsi:type": "MandatParlementaire_type", "uid": "PM722974", "acteurRef": "PA267200", "legislature": "15", "typeOrgane": "ASSEMBLEE", "dateDebut": "2017-06-18", "datePublication": null, "dateFin": null, "preseance": "50", "nominPrincipale": "1", "infosQualite": {"codeQualite": "membre", "libQualite": "membre", "libQualiteSex": "membre"}, "organes": {"organeRef": "PO717460"}, "suppleants": {"suppleant": {"dateDebut": "2017-06-18", "dateFin": null, "suppleantRef": "PA720476"}}, "chambre": null, "election": {"lieu": {"region": "Hauts-de-France", "regionType": "M\u00e9tropolitain", "departement": "Nord", "numDepartement": "59", "numCirco": "5"}, "causeMandat": "\u00e9lections g\u00e9n\u00e9rales", "refCirconscription": "PO717982"}, "mandature": {"datePriseFonction": "2017-06-21", "causeFin": null, "premiereElection": "1", "placeHemicycle": "043", "mandatRemplaceRef": null}, "collaborateurs": {"collaborateur": [{"qualite": "Mme", "prenom": "V\u00e9ronique", "nom": "Van Tichelen-Lestoquoi", "dateDebut": null, "dateFin": null}, {"qualite": "M.", "prenom": "Bastien", "nom": "Dauphin", "dateDebut": null, "dateFin": null}, {"qualite": "Mme", "prenom": "Emeline", "nom": "Clair", "dateDebut": null, "dateFin": null}, {"qualite": "Mme", "prenom": "Brigitte", "nom": "Ferrat", "dateDebut": null, "dateFin": null}]}}]}}}